xcmap/__init__.py
xcmap/configs/__init__.py
xcmap/configs/nacos_center.py
xcmap/configs/nacos_center.py.bak
xcmap/cores/__init__.py
xcmap/cores/chrome/__init__.py
xcmap/cores/chrome/browser.py
xcmap/cores/common/__init__.py
xcmap/cores/common/constant.py
xcmap/cores/common/pydantic_builder.py
xcmap/cores/plugins/__init__.py
xcmap/cores/plugins/interface.py
xcmap/cores/plugins/loader.py
xcmap/cores/queues/__init__.py
xcmap/cores/queues/kafka_queue.py
xcmap/cores/scheduler/__init__.py
xcmap/cores/scheduler/xxl_job.py
xcmap/datasources/DataSourceFactory.py
xcmap/datasources/__init__.py
xcmap/datasources/config.py
xcmap/datasources/mongodb/__init__.py
xcmap/datasources/mysqldb/__init__.py
xcmap/utils/__init__.py
xcmap/utils/cmd_util.py
xcmap/utils/decorator_util.py
xcmap/utils/dict_util.py
xcmap/utils/httpx_util.py
xcmap/utils/image_util.py
xcmap/utils/response_util.py
xcmap/utils/version_util.py
xcmap/utils/win32_util.py
xcmap/utils/yaml_util.py
xcmap-0.1.7.dist-info/METADATA
xcmap-0.1.7.dist-info/WHEEL
xcmap-0.1.7.dist-info/RECORD
