Metadata-Version: 2.3
Name: xcmap
Version: 0.1.7
Summary: 
Author: chuck yang
Author-email: yzhang.baby@gmail.com
Requires-Python: >=3.9
Classifier: Programming Language :: Python :: 3
Classifier: Programming Language :: Python :: 3.9
Classifier: Programming Language :: Python :: 3.10
Classifier: Programming Language :: Python :: 3.11
Classifier: Programming Language :: Python :: 3.12
Classifier: Programming Language :: Python :: 3.13
Provides-Extra: chrome
Provides-Extra: kafka
Provides-Extra: mongo
Provides-Extra: opencv
Provides-Extra: windows
Requires-Dist: confluent-kafka (>=2.12.0,<3.0.0) ; extra == "kafka"
Requires-Dist: drissionpage (>=4.1.0.18,<5.0.0.0) ; extra == "chrome"
Requires-Dist: httpx (>=0.28.1)
Requires-Dist: importlib-metadata (>=8.6.1)
Requires-Dist: mongoengine (>=0.29.1,<1.0.0) ; extra == "mongo"
Requires-Dist: nacos-sdk-python (>=2.0.8,<3.0.0)
Requires-Dist: opencv-python (>=4.11.0.86,<5.0.0) ; extra == "opencv"
Requires-Dist: packaging (>=24.2,<25.0)
Requires-Dist: psutil (>=7.0.0) ; extra == "windows"
Requires-Dist: pydantic (>=2.10.6,<3.0.0)
Requires-Dist: pywin32 (>=310,<311) ; extra == "chrome"
Requires-Dist: pywin32 (>=310,<311) ; extra == "windows"
Requires-Dist: pyyaml (>=6.0.2,<7.0.0)
Requires-Dist: requests (>=2.31.0,<3.0.0)
Requires-Dist: setuptools (>=76.0.0,<80.0.0)
Project-URL: Homepage, https://www.xcmap.cn
